<?xml version="1.0" encoding="utf-8" ?>
<dwsync>
<file name="01.jpg" server="cp23.g-dns.com/Employee/" local="132097236054094113" remote="132097243800000000" />
<file name="02.jpg" server="cp23.g-dns.com/Employee/" local="132097236254499990" remote="132097243800000000" />
<file name="03.jpg" server="cp23.g-dns.com/Employee/" local="132097236481124139" remote="132097247400000000" />
<file name="04.jpg" server="cp23.g-dns.com/Employee/" local="132097247438609518" remote="132097247400000000" />
<file name="05.jpg" server="cp23.g-dns.com/Employee/" local="132097250489338849" remote="132097257600000000" />
<file name="06.jpg" server="cp23.g-dns.com/Employee/" local="132097237440174679" remote="132097257600000000" />
<file name="07.jpg" server="cp23.g-dns.com/Employee/" local="132097237630196069" remote="132097257600000000" />
<file name="08.jpg" server="cp23.g-dns.com/Employee/" local="132097237842763400" remote="132097257600000000" />
<file name="09.jpg" server="cp23.g-dns.com/Employee/" local="132097254337668313" remote="132097257600000000" />
<file name="10.jpg" server="cp23.g-dns.com/Employee/" local="132097238248831641" remote="132097257600000000" />
</dwsync>